odoo/addons/shopinvader_product_stock/README.rst
odoo/addons/shopinvader_product_stock/__init__.py
odoo/addons/shopinvader_product_stock/__manifest__.py
odoo/addons/shopinvader_product_stock/hooks.py
odoo/addons/shopinvader_product_stock/data/ir_export_product.xml
odoo/addons/shopinvader_product_stock/models/__init__.py
odoo/addons/shopinvader_product_stock/models/product_product.py
odoo/addons/shopinvader_product_stock/models/shopinvader_backend.py
odoo/addons/shopinvader_product_stock/models/shopinvader_variant.py
odoo/addons/shopinvader_product_stock/models/stock_move.py
odoo/addons/shopinvader_product_stock/readme/CONTRIBUTORS.rst
odoo/addons/shopinvader_product_stock/readme/CREDITS.rst
odoo/addons/shopinvader_product_stock/readme/DESCRIPTION.rst
odoo/addons/shopinvader_product_stock/readme/HISTORY.rst
odoo/addons/shopinvader_product_stock/static/description/index.html
odoo/addons/shopinvader_product_stock/tests/__init__.py
odoo/addons/shopinvader_product_stock/tests/common.py
odoo/addons/shopinvader_product_stock/tests/test_product.py
odoo/addons/shopinvader_product_stock/tests/test_stock_move.py
odoo/addons/shopinvader_product_stock/views/shopinvader_backend.xml
odoo12_addon_shopinvader_product_stock-12.0.2.0.0.dist-info/METADATA
odoo12_addon_shopinvader_product_stock-12.0.2.0.0.dist-info/WHEEL
odoo12_addon_shopinvader_product_stock-12.0.2.0.0.dist-info/top_level.txt
odoo12_addon_shopinvader_product_stock-12.0.2.0.0.dist-info/RECORD
