Metadata-Version: 2.1
Name: odoo12-addon-shopinvader-product-stock
Version: 12.0.2.0.0
Summary: This module is used to choose a stock field during theexport (by backend)
Home-page: https://github.com/shopinvader/odoo-shopinvader
Author: Akretion,ACSONE SA/NV
License: AGPL-3
Platform: UNKNOWN
Classifier: Programming Language :: Python
Classifier: Framework :: Odoo
Classifier: License :: OSI Approved :: GNU Affero General Public License v3
Classifier: Development Status :: 5 - Production/Stable
Requires-Python: >=3.5
Requires-Dist: odoo12-addon-connector-search-engine
Requires-Dist: odoo12-addon-queue-job
Requires-Dist: odoo12-addon-shopinvader
Requires-Dist: odoo12-addon-shopinvader-search-engine
Requires-Dist: odoo (<12.1dev,>=12.0a)
Requires-Dist: openupgradelib
Requires-Dist: python-slugify (>=3.0.2)
